setup.cfg
setup.py
executioner/__init__.py
executioner/main.py
executioner.egg-info/PKG-INFO
executioner.egg-info/SOURCES.txt
executioner.egg-info/dependency_links.txt
executioner.egg-info/top_level.txt