Metadata-Version: 1.1
Name: executioner
Version: 0.1
Summary: Python framework to convert python objects to CLI applications fast.
Home-page: https://github.com/atf1999/executioner
Author: Tom Orth
Author-email: torth212@gmail.com
License: MIT
Download-URL: https://github.com/atf1999/executioner/tarball/0.1
Platform: UNKNOWN
